setup.py
clipon/__init__.py
clipon/client.py
clipon/clipon.py
clipon/daemon.py
clipon/defines.py
clipon/helper.py
clipon/history.py
clipon.egg-info/PKG-INFO
clipon.egg-info/SOURCES.txt
clipon.egg-info/dependency_links.txt
clipon.egg-info/entry_points.txt
clipon.egg-info/not-zip-safe
clipon.egg-info/requires.txt
clipon.egg-info/top_level.txt