Metadata-Version: 1.1
Name: clipon
Version: 1.0.0
Summary: Clipon - a lightweight clipboard manager
Home-page: https://github.com/jinuxstyle/clipon
Author: Jin Xu
Author-email: jinuxstyle@hotmail.com
License: GPL
Keywords: clipboard,history
Platform: linux
Classifier: Development Status :: 5 - Production/Stable
Classifier: Intended Audience :: End Users/Desktop
Classifier: License :: OSI Approved :: GNU General Public License (GPL)
Classifier: Environment :: Console
Classifier: Natural Language :: English
Classifier: Operating System :: POSIX :: Linux
Classifier: Programming Language :: Python
Classifier: Topic :: Utilities
